{
	"id": "be009083-929d-4797-8a5c-6e154e8e2f75",
	"name": "Dashboard API ENV TEMPLATE",
	"values": [
		{
			"key": "X-Cisco-Meraki-API-Key",
			"value": "",
			"type": "text",
			"enabled": true
		},
		{
			"key": "t0",
			"value": "",
			"type": "text",
			"enabled": true
		},
		{
			"key": "t1",
			"value": "",
			"type": "text",
			"enabled": true
		},
		{
			"key": "timespan",
			"value": "",
			"type": "text",
			"enabled": true
		},
		{
			"key": "perPage",
			"value": "",
			"type": "text",
			"enabled": true
		},
		{
			"key": "startingAfter",
			"value": "",
			"type": "text",
			"enabled": true
		},
		{
			"key": "endingBefore",
			"value": "",
			"type": "text",
			"enabled": true
		},
		{
			"key": "adminId",
			"value": "",
			"type": "text",
			"enabled": true
		},
		{
			"key": "path",
			"value": "",
			"type": "text",
			"enabled": true
		},
		{
			"key": "method",
			"value": "",
			"type": "text",
			"enabled": true
		},
		{
			"key": "responseCode",
			"value": "",
			"type": "text",
			"enabled": true
		},
		{
			"key": "organizationId",
			"value": "",
			"type": "text",
			"enabled": true
		},
		{
			"key": "actionBatchId",
			"value": "",
			"type": "text",
			"enabled": true
		},
		{
			"key": "id",
			"value": "",
			"type": "text",
			"enabled": true
		},
		{
			"key": "networkId",
			"value": "",
			"type": "text",
			"enabled": true
		},
		{
			"key": "includeConnectivityHistory",
			"value": "",
			"type": "text",
			"enabled": true
		},
		{
			"key": "connectivityHistoryTimespan",
			"value": "",
			"type": "text",
			"enabled": true
		},
		{
			"key": "bluetoothClientId",
			"value": "",
			"type": "text",
			"enabled": true
		},
		{
			"key": "serial",
			"value": "",
			"type": "text",
			"enabled": true
		},
		{
			"key": "timestamp",
			"value": "",
			"type": "text",
			"enabled": true
		},
		{
			"key": "clientId",
			"value": "",
			"type": "text",
			"enabled": true
		},
		{
			"key": "resolution",
			"value": "",
			"type": "text",
			"enabled": true
		},
		{
			"key": "configTemplateId",
			"value": "",
			"type": "text",
			"enabled": true
		},
		{
			"key": "uplink",
			"value": "",
			"type": "text",
			"enabled": true
		},
		{
			"key": "ip",
			"value": "",
			"type": "text",
			"enabled": true
		},
		{
			"key": "service",
			"value": "",
			"type": "text",
			"enabled": true
		},
		{
			"key": "groupPolicyId",
			"value": "",
			"type": "text",
			"enabled": true
		},
		{
			"key": "number",
			"value": "",
			"type": "text",
			"enabled": true
		},
		{
			"key": "objectType",
			"value": "",
			"type": "text",
			"enabled": true
		},
		{
			"key": "zoneId",
			"value": "",
			"type": "text",
			"enabled": true
		},
		{
			"key": "appliancePortId",
			"value": "",
			"type": "text",
			"enabled": true
		},
		{
			"key": "merakiAuthUserId",
			"value": "",
			"type": "text",
			"enabled": true
		},
		{
			"key": "withDetails",
			"value": "",
			"type": "text",
			"enabled": true
		},
		{
			"key": "targetGroupId",
			"value": "",
			"type": "text",
			"enabled": true
		},
		{
			"key": "deviceType",
			"value": "",
			"type": "text",
			"enabled": true
		},
		{
			"key": "username",
			"value": "",
			"type": "text",
			"enabled": true
		},
		{
			"key": "email",
			"value": "",
			"type": "text",
			"enabled": true
		},
		{
			"key": "mac",
			"value": "",
			"type": "text",
			"enabled": true
		},
		{
			"key": "imei",
			"value": "",
			"type": "text",
			"enabled": true
		},
		{
			"key": "bluetoothMac",
			"value": "",
			"type": "text",
			"enabled": true
		},
		{
			"key": "requestId",
			"value": "",
			"type": "text",
			"enabled": true
		},
		{
			"key": "includeTemplateProfiles",
			"value": "",
			"type": "text",
			"enabled": true
		},
		{
			"key": "rfProfileId",
			"value": "",
			"type": "text",
			"enabled": true
		},
		{
			"key": "bundleId",
			"value": "",
			"type": "text",
			"enabled": true
		},
		{
			"key": "appId",
			"value": "",
			"type": "text",
			"enabled": true
		},
		{
			"key": "attemptId",
			"value": "",
			"type": "text",
			"enabled": true
		},
		{
			"key": "fields",
			"value": "",
			"type": "text",
			"enabled": true
		},
		{
			"key": "wifiMacs",
			"value": "",
			"type": "text",
			"enabled": true
		},
		{
			"key": "serials",
			"value": "",
			"type": "text",
			"enabled": true
		},
		{
			"key": "ids",
			"value": "",
			"type": "text",
			"enabled": true
		},
		{
			"key": "scope",
			"value": "",
			"type": "text",
			"enabled": true
		},
		{
			"key": "batchToken",
			"value": "",
			"type": "text",
			"enabled": true
		},
		{
			"key": "deviceId",
			"value": "",
			"type": "text",
			"enabled": true
		},
		{
			"key": "profileId",
			"value": "",
			"type": "text",
			"enabled": true
		},
		{
			"key": "userId",
			"value": "",
			"type": "text",
			"enabled": true
		},
		{
			"key": "usernames",
			"value": "",
			"type": "text",
			"enabled": true
		},
		{
			"key": "emails",
			"value": "",
			"type": "text",
			"enabled": true
		},
		{
			"key": "network_id",
			"value": "",
			"type": "text",
			"enabled": true
		},
		{
			"key": "ssidNumber",
			"value": "",
			"type": "text",
			"enabled": true
		},
		{
			"key": "loginIdentifier",
			"value": "",
			"type": "text",
			"enabled": true
		},
		{
			"key": "srId",
			"value": "",
			"type": "text",
			"enabled": true
		},
		{
			"key": "portScheduleId",
			"value": "",
			"type": "text",
			"enabled": true
		},
		{
			"key": "networkID",
			"value": "",
			"type": "text",
			"enabled": true
		},
		{
			"key": "switchStackId",
			"value": "",
			"type": "text",
			"enabled": true
		},
		{
			"key": "vlanId",
			"value": "",
			"type": "text",
			"enabled": true
		},
		{
			"key": "url",
			"value": "",
			"type": "text",
			"enabled": true
		},
		{
			"key": "ssid",
			"value": "",
			"type": "text",
			"enabled": true
		},
		{
			"key": "vlan",
			"value": "",
			"type": "text",
			"enabled": true
		},
		{
			"key": "apTag",
			"value": "",
			"type": "text",
			"enabled": true
		}
	],
	"_postman_variable_scope": "environment",
	"_postman_exported_at": "2020-01-27T08:01:44.647Z",
	"_postman_exported_using": "Postman/7.14.0"
}